[
    {
        "id": 1,
        "name": "John Doe",
        "img": "http://placehold.it/100x100"
    },
    {
        "id": 2,
        "name": "Pauline Halen",
        "img": "http://placehold.it/100x100"
    },
    {
        "id": 3,
        "name": "Matt Hill",
        "img": "http://placehold.it/100x100"
    },
    {
        "id": 4,
        "name": "Jessica Bedford",
        "img": "http://placehold.it/100x100"
    },
    {
        "id": 5,
        "name": "Jessica Alba",
        "img": "http://placehold.it/100x100"
    },
    {
        "id": 6,
        "name": "Scarlett Johansson",
        "img": "http://placehold.it/100x100"
    },
    {
        "id": 7,
        "name": "John Doe",
        "img": "http://placehold.it/100x100"
    },
    {
        "id": 8,
        "name": "Pauline Halen",
        "img": "http://placehold.it/100x100"
    },
    {
        "id": 9,
        "name": "Matt Hill",
        "img": "http://placehold.it/100x100"
    },
    {
        "id": 10,
        "name": "Jessica Bedford",
        "img": "http://placehold.it/100x100"
    },
    {
        "id": 11,
        "name": "Jessica Alba",
        "img": "http://placehold.it/100x100"
    },
    {
        "id": 12,
        "name": "Scarlett Johansson",
        "img": "http://placehold.it/100x100"
    },
    {
        "id": 13,
        "name": "John Doe",
        "img": "http://placehold.it/100x100"
    },
    {
        "id": 14,
        "name": "Pauline Halen",
        "img": "http://placehold.it/100x100"
    },
    {
        "id": 15,
        "name": "Matt Hill",
        "img": "http://placehold.it/100x100"
    },
    {
        "id": 16,
        "name": "Jessica Bedford",
        "img": "http://placehold.it/100x100"
    },
    {
        "id": 17,
        "name": "Jessica Alba",
        "img": "http://placehold.it/100x100"
    },
    {
        "id": 18,
        "name": "Scarlett Johansson",
        "img": "http://placehold.it/100x100"
    },
    {
        "id": 19,
        "name": "John Doe",
        "img": "http://placehold.it/100x100"
    },
    {
        "id": 20,
        "name": "Pauline Halen",
        "img": "http://placehold.it/100x100"
    },
    {
        "id": 21,
        "name": "Matt Hill",
        "img": "http://placehold.it/100x100"
    },
    {
        "id": 22,
        "name": "Jessica Bedford",
        "img": "http://placehold.it/100x100"
    },
    {
        "id": 23,
        "name": "Jessica Alba",
        "img": "http://placehold.it/100x100"
    },
    {
        "id": 24,
        "name": "Scarlett Johansson",
        "img": "http://placehold.it/100x100"
    },
    {
        "id": 25,
        "name": "John Doe",
        "img": "http://placehold.it/100x100"
    },
    {
        "id": 26,
        "name": "Pauline Halen",
        "img": "http://placehold.it/100x100"
    },
    {
        "id": 27,
        "name": "Matt Hill",
        "img": "http://placehold.it/100x100"
    },
    {
        "id": 28,
        "name": "Jessica Bedford",
        "img": "http://placehold.it/100x100"
    },
    {
        "id": 29,
        "name": "Jessica Alba",
        "img": "http://placehold.it/100x100"
    },
    {
        "id": 30,
        "name": "Scarlett Johansson",
        "img": "http://placehold.it/100x100"
    },
    {
        "id": 31,
        "name": "John Doe",
        "img": "http://placehold.it/100x100"
    },
    {
        "id": 32,
        "name": "Pauline Halen",
        "img": "http://placehold.it/100x100"
    },
    {
        "id": 33,
        "name": "Matt Hill",
        "img": "http://placehold.it/100x100"
    },
    {
        "id": 34,
        "name": "Jessica Bedford",
        "img": "http://placehold.it/100x100"
    },
    {
        "id": 35,
        "name": "Jessica Alba",
        "img": "http://placehold.it/100x100"
    },
    {
        "id": 36,
        "name": "Scarlett Johansson",
        "img": "http://placehold.it/100x100"
    },
    {
        "id": 37,
        "name": "John Doe",
        "img": "http://placehold.it/100x100"
    },
    {
        "id": 38,
        "name": "Pauline Halen",
        "img": "http://placehold.it/100x100"
    },
    {
        "id": 39,
        "name": "Matt Hill",
        "img": "http://placehold.it/100x100"
    },
    {
        "id": 40,
        "name": "Jessica Bedford",
        "img": "http://placehold.it/100x100"
    },
    {
        "id": 41,
        "name": "Jessica Alba",
        "img": "http://placehold.it/100x100"
    },
    {
        "id": 42,
        "name": "Scarlett Johansson",
        "img": "http://placehold.it/100x100"
    },
    {
        "id": 43,
        "name": "John Doe",
        "img": "http://placehold.it/100x100"
    },
    {
        "id": 44,
        "name": "Pauline Halen",
        "img": "http://placehold.it/100x100"
    },
    {
        "id": 45,
        "name": "Matt Hill",
        "img": "http://placehold.it/100x100"
    },
    {
        "id": 46,
        "name": "Jessica Bedford",
        "img": "http://placehold.it/100x100"
    },
    {
        "id": 47,
        "name": "Jessica Alba",
        "img": "http://placehold.it/100x100"
    },
    {
        "id": 48,
        "name": "Scarlett Johansson",
        "img": "http://placehold.it/100x100"
    },
    {
        "id": 49,
        "name": "John Doe",
        "img": "http://placehold.it/100x100"
    },
    {
        "id": 50,
        "name": "Pauline Halen",
        "img": "http://placehold.it/100x100"
    },
    {
        "id": 51,
        "name": "Matt Hill",
        "img": "http://placehold.it/100x100"
    },
    {
        "id": 52,
        "name": "Jessica Bedford",
        "img": "http://placehold.it/100x100"
    },
    {
        "id": 53,
        "name": "Jessica Alba",
        "img": "http://placehold.it/100x100"
    },
    {
        "id": 54,
        "name": "Scarlett Johansson",
        "img": "http://placehold.it/100x100"
    },
    {
        "id": 55,
        "name": "John Doe",
        "img": "http://placehold.it/100x100"
    },
    {
        "id": 56,
        "name": "Pauline Halen",
        "img": "http://placehold.it/100x100"
    },
    {
        "id": 57,
        "name": "Matt Hill",
        "img": "http://placehold.it/100x100"
    },
    {
        "id": 58,
        "name": "Jessica Bedford",
        "img": "http://placehold.it/100x100"
    },
    {
        "id": 59,
        "name": "Jessica Alba",
        "img": "http://placehold.it/100x100"
    },
    {
        "id": 60,
        "name": "Scarlett Johansson",
        "img": "http://placehold.it/100x100"
    },
    {
        "id": 61,
        "name": "John Doe",
        "img": "http://placehold.it/100x100"
    },
    {
        "id": 62,
        "name": "Pauline Halen",
        "img": "http://placehold.it/100x100"
    },
    {
        "id": 63,
        "name": "Matt Hill",
        "img": "http://placehold.it/100x100"
    },
    {
        "id": 64,
        "name": "Jessica Bedford",
        "img": "http://placehold.it/100x100"
    },
    {
        "id": 65,
        "name": "Jessica Alba",
        "img": "http://placehold.it/100x100"
    },
    {
        "id": 66,
        "name": "Scarlett Johansson",
        "img": "http://placehold.it/100x100"
    },
    {
        "id": 67,
        "name": "John Doe",
        "img": "http://placehold.it/100x100"
    },
    {
        "id": 68,
        "name": "Pauline Halen",
        "img": "http://placehold.it/100x100"
    },
    {
        "id": 69,
        "name": "Matt Hill",
        "img": "http://placehold.it/100x100"
    },
    {
        "id": 70,
        "name": "Jessica Bedford",
        "img": "http://placehold.it/100x100"
    },
    {
        "id": 71,
        "name": "Jessica Alba",
        "img": "http://placehold.it/100x100"
    },
    {
        "id": 72,
        "name": "Scarlett Johansson",
        "img": "http://placehold.it/100x100"
    },
    {
        "id": 73,
        "name": "John Doe",
        "img": "http://placehold.it/100x100"
    },
    {
        "id": 74,
        "name": "Pauline Halen",
        "img": "http://placehold.it/100x100"
    },
    {
        "id": 75,
        "name": "Matt Hill",
        "img": "http://placehold.it/100x100"
    },
    {
        "id": 76,
        "name": "Jessica Bedford",
        "img": "http://placehold.it/100x100"
    },
    {
        "id": 77,
        "name": "Jessica Alba",
        "img": "http://placehold.it/100x100"
    },
    {
        "id": 78,
        "name": "Scarlett Johansson",
        "img": "http://placehold.it/100x100"
    },
    {
        "id": 79,
        "name": "John Doe",
        "img": "http://placehold.it/100x100"
    },
    {
        "id": 80,
        "name": "Pauline Halen",
        "img": "http://placehold.it/100x100"
    },
    {
        "id": 81,
        "name": "Matt Hill",
        "img": "http://placehold.it/100x100"
    },
    {
        "id": 82,
        "name": "Jessica Bedford",
        "img": "http://placehold.it/100x100"
    },
    {
        "id": 83,
        "name": "Jessica Alba",
        "img": "http://placehold.it/100x100"
    },
    {
        "id": 84,
        "name": "Scarlett Johansson",
        "img": "http://placehold.it/100x100"
    },
    {
        "id": 85,
        "name": "John Doe",
        "img": "http://placehold.it/100x100"
    },
    {
        "id": 86,
        "name": "Pauline Halen",
        "img": "http://placehold.it/100x100"
    },
    {
        "id": 87,
        "name": "Matt Hill",
        "img": "http://placehold.it/100x100"
    },
    {
        "id": 88,
        "name": "Jessica Bedford",
        "img": "http://placehold.it/100x100"
    },
    {
        "id": 89,
        "name": "Jessica Alba",
        "img": "http://placehold.it/100x100"
    },
    {
        "id": 90,
        "name": "Scarlett Johansson",
        "img": "http://placehold.it/100x100"
    },
    {
        "id": 91,
        "name": "John Doe",
        "img": "http://placehold.it/100x100"
    },
    {
        "id": 92,
        "name": "Pauline Halen",
        "img": "http://placehold.it/100x100"
    },
    {
        "id": 93,
        "name": "Matt Hill",
        "img": "http://placehold.it/100x100"
    },
    {
        "id": 94,
        "name": "Jessica Bedford",
        "img": "http://placehold.it/100x100"
    },
    {
        "id": 95,
        "name": "Jessica Alba",
        "img": "http://placehold.it/100x100"
    },
    {
        "id": 96,
        "name": "Scarlett Johansson",
        "img": "http://placehold.it/100x100"
    },
    {
        "id": 97,
        "name": "John Doe",
        "img": "http://placehold.it/100x100"
    },
    {
        "id": 98,
        "name": "Pauline Halen",
        "img": "http://placehold.it/100x100"
    },
    {
        "id": 99,
        "name": "Matt Hill",
        "img": "http://placehold.it/100x100"
    },
    {
        "id": 100,
        "name": "Jessica Bedford",
        "img": "http://placehold.it/100x100"
    },
    {
        "id": 101,
        "name": "Jessica Alba",
        "img": "http://placehold.it/100x100"
    },
    {
        "id": 102,
        "name": "Scarlett Johansson",
        "img": "http://placehold.it/100x100"
    },
    {
        "id": 103,
        "name": "John Doe",
        "img": "http://placehold.it/100x100"
    },
    {
        "id": 104,
        "name": "Pauline Halen",
        "img": "http://placehold.it/100x100"
    },
    {
        "id": 105,
        "name": "Matt Hill",
        "img": "http://placehold.it/100x100"
    },
    {
        "id": 106,
        "name": "Jessica Bedford",
        "img": "http://placehold.it/100x100"
    },
    {
        "id": 107,
        "name": "Jessica Alba",
        "img": "http://placehold.it/100x100"
    },
    {
        "id": 108,
        "name": "Scarlett Johansson",
        "img": "http://placehold.it/100x100"
    },
    {
        "id": 109,
        "name": "John Doe",
        "img": "http://placehold.it/100x100"
    },
    {
        "id": 110,
        "name": "Pauline Halen",
        "img": "http://placehold.it/100x100"
    },
    {
        "id": 111,
        "name": "Matt Hill",
        "img": "http://placehold.it/100x100"
    },
    {
        "id": 112,
        "name": "Jessica Bedford",
        "img": "http://placehold.it/100x100"
    },
    {
        "id": 113,
        "name": "Jessica Alba",
        "img": "http://placehold.it/100x100"
    },
    {
        "id": 114,
        "name": "Scarlett Johansson",
        "img": "http://placehold.it/100x100"
    },
    {
        "id": 115,
        "name": "John Doe",
        "img": "http://placehold.it/100x100"
    },
    {
        "id": 116,
        "name": "Pauline Halen",
        "img": "http://placehold.it/100x100"
    },
    {
        "id": 117,
        "name": "Matt Hill",
        "img": "http://placehold.it/100x100"
    },
    {
        "id": 118,
        "name": "Jessica Bedford",
        "img": "http://placehold.it/100x100"
    },
    {
        "id": 119,
        "name": "Jessica Alba",
        "img": "http://placehold.it/100x100"
    },
    {
        "id": 120,
        "name": "Scarlett Johansson",
        "img": "http://placehold.it/100x100"
    },
    {
        "id": 121,
        "name": "John Doe",
        "img": "http://placehold.it/100x100"
    },
    {
        "id": 122,
        "name": "Pauline Halen",
        "img": "http://placehold.it/100x100"
    },
    {
        "id": 123,
        "name": "Matt Hill",
        "img": "http://placehold.it/100x100"
    },
    {
        "id": 124,
        "name": "Jessica Bedford",
        "img": "http://placehold.it/100x100"
    },
    {
        "id": 125,
        "name": "Jessica Alba",
        "img": "http://placehold.it/100x100"
    },
    {
        "id": 126,
        "name": "Scarlett Johansson",
        "img": "http://placehold.it/100x100"
    },
    {
        "id": 127,
        "name": "John Doe",
        "img": "http://placehold.it/100x100"
    },
    {
        "id": 128,
        "name": "Pauline Halen",
        "img": "http://placehold.it/100x100"
    },
    {
        "id": 129,
        "name": "Matt Hill",
        "img": "http://placehold.it/100x100"
    },
    {
        "id": 130,
        "name": "Jessica Bedford",
        "img": "http://placehold.it/100x100"
    },
    {
        "id": 131,
        "name": "Jessica Alba",
        "img": "http://placehold.it/100x100"
    },
    {
        "id": 132,
        "name": "Scarlett Johansson",
        "img": "http://placehold.it/100x100"
    },
    {
        "id": 133,
        "name": "John Doe",
        "img": "http://placehold.it/100x100"
    },
    {
        "id": 134,
        "name": "Pauline Halen",
        "img": "http://placehold.it/100x100"
    },
    {
        "id": 135,
        "name": "Matt Hill",
        "img": "http://placehold.it/100x100"
    },
    {
        "id": 136,
        "name": "Jessica Bedford",
        "img": "http://placehold.it/100x100"
    },
    {
        "id": 137,
        "name": "Jessica Alba",
        "img": "http://placehold.it/100x100"
    },
    {
        "id": 138,
        "name": "Scarlett Johansson",
        "img": "http://placehold.it/100x100"
    },
    {
        "id": 139,
        "name": "John Doe",
        "img": "http://placehold.it/100x100"
    },
    {
        "id": 140,
        "name": "Pauline Halen",
        "img": "http://placehold.it/100x100"
    },
    {
        "id": 141,
        "name": "Matt Hill",
        "img": "http://placehold.it/100x100"
    },
    {
        "id": 142,
        "name": "Jessica Bedford",
        "img": "http://placehold.it/100x100"
    },
    {
        "id": 143,
        "name": "Jessica Alba",
        "img": "http://placehold.it/100x100"
    },
    {
        "id": 144,
        "name": "Scarlett Johansson",
        "img": "http://placehold.it/100x100"
    },
    {
        "id": 145,
        "name": "John Doe",
        "img": "http://placehold.it/100x100"
    },
    {
        "id": 146,
        "name": "Pauline Halen",
        "img": "http://placehold.it/100x100"
    },
    {
        "id": 147,
        "name": "Matt Hill",
        "img": "http://placehold.it/100x100"
    },
    {
        "id": 148,
        "name": "Jessica Bedford",
        "img": "http://placehold.it/100x100"
    },
    {
        "id": 149,
        "name": "Jessica Alba",
        "img": "http://placehold.it/100x100"
    },
    {
        "id": 150,
        "name": "Scarlett Johansson",
        "img": "http://placehold.it/100x100"
    },
    {
        "id": 151,
        "name": "John Doe",
        "img": "http://placehold.it/100x100"
    },
    {
        "id": 152,
        "name": "Pauline Halen",
        "img": "http://placehold.it/100x100"
    },
    {
        "id": 153,
        "name": "Matt Hill",
        "img": "http://placehold.it/100x100"
    },
    {
        "id": 154,
        "name": "Jessica Bedford",
        "img": "http://placehold.it/100x100"
    },
    {
        "id": 155,
        "name": "Jessica Alba",
        "img": "http://placehold.it/100x100"
    },
    {
        "id": 156,
        "name": "Scarlett Johansson",
        "img": "http://placehold.it/100x100"
    },
    {
        "id": 157,
        "name": "John Doe",
        "img": "http://placehold.it/100x100"
    },
    {
        "id": 158,
        "name": "Pauline Halen",
        "img": "http://placehold.it/100x100"
    },
    {
        "id": 159,
        "name": "Matt Hill",
        "img": "http://placehold.it/100x100"
    },
    {
        "id": 160,
        "name": "Jessica Bedford",
        "img": "http://placehold.it/100x100"
    },
    {
        "id": 161,
        "name": "Jessica Alba",
        "img": "http://placehold.it/100x100"
    },
    {
        "id": 162,
        "name": "Scarlett Johansson",
        "img": "http://placehold.it/100x100"
    },
    {
        "id": 163,
        "name": "John Doe",
        "img": "http://placehold.it/100x100"
    },
    {
        "id": 164,
        "name": "Pauline Halen",
        "img": "http://placehold.it/100x100"
    },
    {
        "id": 165,
        "name": "Matt Hill",
        "img": "http://placehold.it/100x100"
    },
    {
        "id": 166,
        "name": "Jessica Bedford",
        "img": "http://placehold.it/100x100"
    },
    {
        "id": 167,
        "name": "Jessica Alba",
        "img": "http://placehold.it/100x100"
    },
    {
        "id": 168,
        "name": "Scarlett Johansson",
        "img": "http://placehold.it/100x100"
    },
    {
        "id": 169,
        "name": "John Doe",
        "img": "http://placehold.it/100x100"
    },
    {
        "id": 170,
        "name": "Pauline Halen",
        "img": "http://placehold.it/100x100"
    },
    {
        "id": 171,
        "name": "Matt Hill",
        "img": "http://placehold.it/100x100"
    },
    {
        "id": 172,
        "name": "Jessica Bedford",
        "img": "http://placehold.it/100x100"
    },
    {
        "id": 173,
        "name": "Jessica Alba",
        "img": "http://placehold.it/100x100"
    },
    {
        "id": 174,
        "name": "Scarlett Johansson",
        "img": "http://placehold.it/100x100"
    },
    {
        "id": 175,
        "name": "John Doe",
        "img": "http://placehold.it/100x100"
    },
    {
        "id": 176,
        "name": "Pauline Halen",
        "img": "http://placehold.it/100x100"
    },
    {
        "id": 177,
        "name": "Matt Hill",
        "img": "http://placehold.it/100x100"
    },
    {
        "id": 178,
        "name": "Jessica Bedford",
        "img": "http://placehold.it/100x100"
    },
    {
        "id": 179,
        "name": "Jessica Alba",
        "img": "http://placehold.it/100x100"
    },
    {
        "id": 180,
        "name": "Scarlett Johansson",
        "img": "http://placehold.it/100x100"
    },
    {
        "id": 181,
        "name": "John Doe",
        "img": "http://placehold.it/100x100"
    },
    {
        "id": 182,
        "name": "Pauline Halen",
        "img": "http://placehold.it/100x100"
    },
    {
        "id": 183,
        "name": "Matt Hill",
        "img": "http://placehold.it/100x100"
    },
    {
        "id": 184,
        "name": "Jessica Bedford",
        "img": "http://placehold.it/100x100"
    },
    {
        "id": 185,
        "name": "Jessica Alba",
        "img": "http://placehold.it/100x100"
    },
    {
        "id": 186,
        "name": "Scarlett Johansson",
        "img": "http://placehold.it/100x100"
    },
    {
        "id": 187,
        "name": "John Doe",
        "img": "http://placehold.it/100x100"
    },
    {
        "id": 188,
        "name": "Pauline Halen",
        "img": "http://placehold.it/100x100"
    },
    {
        "id": 189,
        "name": "Matt Hill",
        "img": "http://placehold.it/100x100"
    },
    {
        "id": 190,
        "name": "Jessica Bedford",
        "img": "http://placehold.it/100x100"
    },
    {
        "id": 191,
        "name": "Jessica Alba",
        "img": "http://placehold.it/100x100"
    },
    {
        "id": 192,
        "name": "Scarlett Johansson",
        "img": "http://placehold.it/100x100"
    },
    {
        "id": 193,
        "name": "John Doe",
        "img": "http://placehold.it/100x100"
    },
    {
        "id": 194,
        "name": "Pauline Halen",
        "img": "http://placehold.it/100x100"
    },
    {
        "id": 195,
        "name": "Matt Hill",
        "img": "http://placehold.it/100x100"
    },
    {
        "id": 196,
        "name": "Jessica Bedford",
        "img": "http://placehold.it/100x100"
    },
    {
        "id": 197,
        "name": "Jessica Alba",
        "img": "http://placehold.it/100x100"
    },
    {
        "id": 198,
        "name": "Scarlett Johansson",
        "img": "http://placehold.it/100x100"
    },
    {
        "id": 199,
        "name": "John Doe",
        "img": "http://placehold.it/100x100"
    },
    {
        "id": 200,
        "name": "Pauline Halen",
        "img": "http://placehold.it/100x100"
    },
    {
        "id": 201,
        "name": "Matt Hill",
        "img": "http://placehold.it/100x100"
    },
    {
        "id": 202,
        "name": "Jessica Bedford",
        "img": "http://placehold.it/100x100"
    },
    {
        "id": 203,
        "name": "Jessica Alba",
        "img": "http://placehold.it/100x100"
    },
    {
        "id": 204,
        "name": "Scarlett Johansson",
        "img": "http://placehold.it/100x100"
    },
    {
        "id": 205,
        "name": "John Doe",
        "img": "http://placehold.it/100x100"
    },
    {
        "id": 206,
        "name": "Pauline Halen",
        "img": "http://placehold.it/100x100"
    },
    {
        "id": 207,
        "name": "Matt Hill",
        "img": "http://placehold.it/100x100"
    },
    {
        "id": 208,
        "name": "Jessica Bedford",
        "img": "http://placehold.it/100x100"
    },
    {
        "id": 209,
        "name": "Jessica Alba",
        "img": "http://placehold.it/100x100"
    },
    {
        "id": 210,
        "name": "Scarlett Johansson",
        "img": "http://placehold.it/100x100"
    },
    {
        "id": 211,
        "name": "John Doe",
        "img": "http://placehold.it/100x100"
    },
    {
        "id": 212,
        "name": "Pauline Halen",
        "img": "http://placehold.it/100x100"
    },
    {
        "id": 213,
        "name": "Matt Hill",
        "img": "http://placehold.it/100x100"
    },
    {
        "id": 214,
        "name": "Jessica Bedford",
        "img": "http://placehold.it/100x100"
    },
    {
        "id": 215,
        "name": "Jessica Alba",
        "img": "http://placehold.it/100x100"
    },
    {
        "id": 216,
        "name": "Scarlett Johansson",
        "img": "http://placehold.it/100x100"
    },
    {
        "id": 217,
        "name": "John Doe",
        "img": "http://placehold.it/100x100"
    },
    {
        "id": 218,
        "name": "Pauline Halen",
        "img": "http://placehold.it/100x100"
    },
    {
        "id": 219,
        "name": "Matt Hill",
        "img": "http://placehold.it/100x100"
    },
    {
        "id": 220,
        "name": "Jessica Bedford",
        "img": "http://placehold.it/100x100"
    },
    {
        "id": 221,
        "name": "Jessica Alba",
        "img": "http://placehold.it/100x100"
    },
    {
        "id": 222,
        "name": "Scarlett Johansson",
        "img": "http://placehold.it/100x100"
    },
    {
        "id": 223,
        "name": "John Doe",
        "img": "http://placehold.it/100x100"
    },
    {
        "id": 224,
        "name": "Pauline Halen",
        "img": "http://placehold.it/100x100"
    },
    {
        "id": 225,
        "name": "Matt Hill",
        "img": "http://placehold.it/100x100"
    },
    {
        "id": 226,
        "name": "Jessica Bedford",
        "img": "http://placehold.it/100x100"
    },
    {
        "id": 227,
        "name": "Jessica Alba",
        "img": "http://placehold.it/100x100"
    },
    {
        "id": 228,
        "name": "Scarlett Johansson",
        "img": "http://placehold.it/100x100"
    },
    {
        "id": 229,
        "name": "John Doe",
        "img": "http://placehold.it/100x100"
    },
    {
        "id": 230,
        "name": "Pauline Halen",
        "img": "http://placehold.it/100x100"
    },
    {
        "id": 231,
        "name": "Matt Hill",
        "img": "http://placehold.it/100x100"
    },
    {
        "id": 232,
        "name": "Jessica Bedford",
        "img": "http://placehold.it/100x100"
    },
    {
        "id": 233,
        "name": "Jessica Alba",
        "img": "http://placehold.it/100x100"
    },
    {
        "id": 234,
        "name": "Scarlett Johansson",
        "img": "http://placehold.it/100x100"
    },
    {
        "id": 235,
        "name": "John Doe",
        "img": "http://placehold.it/100x100"
    },
    {
        "id": 236,
        "name": "Pauline Halen",
        "img": "http://placehold.it/100x100"
    },
    {
        "id": 237,
        "name": "Matt Hill",
        "img": "http://placehold.it/100x100"
    },
    {
        "id": 238,
        "name": "Jessica Bedford",
        "img": "http://placehold.it/100x100"
    },
    {
        "id": 239,
        "name": "Jessica Alba",
        "img": "http://placehold.it/100x100"
    },
    {
        "id": 240,
        "name": "Scarlett Johansson",
        "img": "http://placehold.it/100x100"
    },
    {
        "id": 241,
        "name": "John Doe",
        "img": "http://placehold.it/100x100"
    },
    {
        "id": 242,
        "name": "Pauline Halen",
        "img": "http://placehold.it/100x100"
    },
    {
        "id": 243,
        "name": "Matt Hill",
        "img": "http://placehold.it/100x100"
    },
    {
        "id": 244,
        "name": "Jessica Bedford",
        "img": "http://placehold.it/100x100"
    },
    {
        "id": 245,
        "name": "Jessica Alba",
        "img": "http://placehold.it/100x100"
    },
    {
        "id": 246,
        "name": "Scarlett Johansson",
        "img": "http://placehold.it/100x100"
    },
    {
        "id": 247,
        "name": "John Doe",
        "img": "http://placehold.it/100x100"
    },
    {
        "id": 248,
        "name": "Pauline Halen",
        "img": "http://placehold.it/100x100"
    },
    {
        "id": 249,
        "name": "Matt Hill",
        "img": "http://placehold.it/100x100"
    },
    {
        "id": 250,
        "name": "Jessica Bedford",
        "img": "http://placehold.it/100x100"
    },
    {
        "id": 251,
        "name": "Jessica Alba",
        "img": "http://placehold.it/100x100"
    },
    {
        "id": 252,
        "name": "Scarlett Johansson",
        "img": "http://placehold.it/100x100"
    },
    {
        "id": 253,
        "name": "John Doe",
        "img": "http://placehold.it/100x100"
    },
    {
        "id": 254,
        "name": "Pauline Halen",
        "img": "http://placehold.it/100x100"
    },
    {
        "id": 255,
        "name": "Matt Hill",
        "img": "http://placehold.it/100x100"
    },
    {
        "id": 256,
        "name": "Jessica Bedford",
        "img": "http://placehold.it/100x100"
    },
    {
        "id": 257,
        "name": "Jessica Alba",
        "img": "http://placehold.it/100x100"
    },
    {
        "id": 258,
        "name": "Scarlett Johansson",
        "img": "http://placehold.it/100x100"
    },
    {
        "id": 259,
        "name": "John Doe",
        "img": "http://placehold.it/100x100"
    },
    {
        "id": 260,
        "name": "Pauline Halen",
        "img": "http://placehold.it/100x100"
    },
    {
        "id": 261,
        "name": "Matt Hill",
        "img": "http://placehold.it/100x100"
    },
    {
        "id": 262,
        "name": "Jessica Bedford",
        "img": "http://placehold.it/100x100"
    },
    {
        "id": 263,
        "name": "Jessica Alba",
        "img": "http://placehold.it/100x100"
    },
    {
        "id": 264,
        "name": "Scarlett Johansson",
        "img": "http://placehold.it/100x100"
    },
    {
        "id": 265,
        "name": "John Doe",
        "img": "http://placehold.it/100x100"
    },
    {
        "id": 266,
        "name": "Pauline Halen",
        "img": "http://placehold.it/100x100"
    },
    {
        "id": 267,
        "name": "Matt Hill",
        "img": "http://placehold.it/100x100"
    },
    {
        "id": 268,
        "name": "Jessica Bedford",
        "img": "http://placehold.it/100x100"
    },
    {
        "id": 269,
        "name": "Jessica Alba",
        "img": "http://placehold.it/100x100"
    },
    {
        "id": 270,
        "name": "Scarlett Johansson",
        "img": "http://placehold.it/100x100"
    },
    {
        "id": 271,
        "name": "John Doe",
        "img": "http://placehold.it/100x100"
    },
    {
        "id": 272,
        "name": "Pauline Halen",
        "img": "http://placehold.it/100x100"
    },
    {
        "id": 273,
        "name": "Matt Hill",
        "img": "http://placehold.it/100x100"
    },
    {
        "id": 274,
        "name": "Jessica Bedford",
        "img": "http://placehold.it/100x100"
    },
    {
        "id": 275,
        "name": "Jessica Alba",
        "img": "http://placehold.it/100x100"
    },
    {
        "id": 276,
        "name": "Scarlett Johansson",
        "img": "http://placehold.it/100x100"
    },
    {
        "id": 277,
        "name": "John Doe",
        "img": "http://placehold.it/100x100"
    },
    {
        "id": 278,
        "name": "Pauline Halen",
        "img": "http://placehold.it/100x100"
    },
    {
        "id": 279,
        "name": "Matt Hill",
        "img": "http://placehold.it/100x100"
    },
    {
        "id": 280,
        "name": "Jessica Bedford",
        "img": "http://placehold.it/100x100"
    },
    {
        "id": 281,
        "name": "Jessica Alba",
        "img": "http://placehold.it/100x100"
    },
    {
        "id": 282,
        "name": "Scarlett Johansson",
        "img": "http://placehold.it/100x100"
    },
    {
        "id": 283,
        "name": "John Doe",
        "img": "http://placehold.it/100x100"
    },
    {
        "id": 284,
        "name": "Pauline Halen",
        "img": "http://placehold.it/100x100"
    },
    {
        "id": 285,
        "name": "Matt Hill",
        "img": "http://placehold.it/100x100"
    },
    {
        "id": 286,
        "name": "Jessica Bedford",
        "img": "http://placehold.it/100x100"
    },
    {
        "id": 287,
        "name": "Jessica Alba",
        "img": "http://placehold.it/100x100"
    },
    {
        "id": 288,
        "name": "Scarlett Johansson",
        "img": "http://placehold.it/100x100"
    },
    {
        "id": 289,
        "name": "John Doe",
        "img": "http://placehold.it/100x100"
    },
    {
        "id": 290,
        "name": "Pauline Halen",
        "img": "http://placehold.it/100x100"
    },
    {
        "id": 291,
        "name": "Matt Hill",
        "img": "http://placehold.it/100x100"
    },
    {
        "id": 292,
        "name": "Jessica Bedford",
        "img": "http://placehold.it/100x100"
    },
    {
        "id": 293,
        "name": "Jessica Alba",
        "img": "http://placehold.it/100x100"
    },
    {
        "id": 294,
        "name": "Scarlett Johansson",
        "img": "http://placehold.it/100x100"
    },
    {
        "id": 295,
        "name": "John Doe",
        "img": "http://placehold.it/100x100"
    },
    {
        "id": 296,
        "name": "Pauline Halen",
        "img": "http://placehold.it/100x100"
    },
    {
        "id": 297,
        "name": "Matt Hill",
        "img": "http://placehold.it/100x100"
    },
    {
        "id": 298,
        "name": "Jessica Bedford",
        "img": "http://placehold.it/100x100"
    },
    {
        "id": 299,
        "name": "Jessica Alba",
        "img": "http://placehold.it/100x100"
    },
    {
        "id": 300,
        "name": "Scarlett Johansson",
        "img": "http://placehold.it/100x100"
    },
    {
        "id": 301,
        "name": "John Doe",
        "img": "http://placehold.it/100x100"
    },
    {
        "id": 302,
        "name": "Pauline Halen",
        "img": "http://placehold.it/100x100"
    },
    {
        "id": 303,
        "name": "Matt Hill",
        "img": "http://placehold.it/100x100"
    },
    {
        "id": 304,
        "name": "Jessica Bedford",
        "img": "http://placehold.it/100x100"
    },
    {
        "id": 305,
        "name": "Jessica Alba",
        "img": "http://placehold.it/100x100"
    },
    {
        "id": 306,
        "name": "Scarlett Johansson",
        "img": "http://placehold.it/100x100"
    },
    {
        "id": 307,
        "name": "John Doe",
        "img": "http://placehold.it/100x100"
    },
    {
        "id": 308,
        "name": "Pauline Halen",
        "img": "http://placehold.it/100x100"
    },
    {
        "id": 309,
        "name": "Matt Hill",
        "img": "http://placehold.it/100x100"
    },
    {
        "id": 310,
        "name": "Jessica Bedford",
        "img": "http://placehold.it/100x100"
    },
    {
        "id": 311,
        "name": "Jessica Alba",
        "img": "http://placehold.it/100x100"
    },
    {
        "id": 312,
        "name": "Scarlett Johansson",
        "img": "http://placehold.it/100x100"
    },
    {
        "id": 313,
        "name": "John Doe",
        "img": "http://placehold.it/100x100"
    },
    {
        "id": 314,
        "name": "Pauline Halen",
        "img": "http://placehold.it/100x100"
    },
    {
        "id": 315,
        "name": "Matt Hill",
        "img": "http://placehold.it/100x100"
    },
    {
        "id": 316,
        "name": "Jessica Bedford",
        "img": "http://placehold.it/100x100"
    },
    {
        "id": 317,
        "name": "Jessica Alba",
        "img": "http://placehold.it/100x100"
    },
    {
        "id": 318,
        "name": "Scarlett Johansson",
        "img": "http://placehold.it/100x100"
    },
    {
        "id": 319,
        "name": "John Doe",
        "img": "http://placehold.it/100x100"
    },
    {
        "id": 320,
        "name": "Pauline Halen",
        "img": "http://placehold.it/100x100"
    },
    {
        "id": 321,
        "name": "Matt Hill",
        "img": "http://placehold.it/100x100"
    },
    {
        "id": 322,
        "name": "Jessica Bedford",
        "img": "http://placehold.it/100x100"
    },
    {
        "id": 323,
        "name": "Jessica Alba",
        "img": "http://placehold.it/100x100"
    },
    {
        "id": 324,
        "name": "Scarlett Johansson",
        "img": "http://placehold.it/100x100"
    },
    {
        "id": 325,
        "name": "John Doe",
        "img": "http://placehold.it/100x100"
    },
    {
        "id": 326,
        "name": "Pauline Halen",
        "img": "http://placehold.it/100x100"
    },
    {
        "id": 327,
        "name": "Matt Hill",
        "img": "http://placehold.it/100x100"
    },
    {
        "id": 328,
        "name": "Jessica Bedford",
        "img": "http://placehold.it/100x100"
    },
    {
        "id": 329,
        "name": "Jessica Alba",
        "img": "http://placehold.it/100x100"
    },
    {
        "id": 330,
        "name": "Scarlett Johansson",
        "img": "http://placehold.it/100x100"
    },
    {
        "id": 331,
        "name": "John Doe",
        "img": "http://placehold.it/100x100"
    },
    {
        "id": 332,
        "name": "Pauline Halen",
        "img": "http://placehold.it/100x100"
    },
    {
        "id": 333,
        "name": "Matt Hill",
        "img": "http://placehold.it/100x100"
    },
    {
        "id": 334,
        "name": "Jessica Bedford",
        "img": "http://placehold.it/100x100"
    },
    {
        "id": 335,
        "name": "Jessica Alba",
        "img": "http://placehold.it/100x100"
    },
    {
        "id": 336,
        "name": "Scarlett Johansson",
        "img": "http://placehold.it/100x100"
    },
    {
        "id": 337,
        "name": "John Doe",
        "img": "http://placehold.it/100x100"
    },
    {
        "id": 338,
        "name": "Pauline Halen",
        "img": "http://placehold.it/100x100"
    },
    {
        "id": 339,
        "name": "Matt Hill",
        "img": "http://placehold.it/100x100"
    },
    {
        "id": 340,
        "name": "Jessica Bedford",
        "img": "http://placehold.it/100x100"
    },
    {
        "id": 341,
        "name": "Jessica Alba",
        "img": "http://placehold.it/100x100"
    },
    {
        "id": 342,
        "name": "Scarlett Johansson",
        "img": "http://placehold.it/100x100"
    },
    {
        "id": 343,
        "name": "John Doe",
        "img": "http://placehold.it/100x100"
    },
    {
        "id": 344,
        "name": "Pauline Halen",
        "img": "http://placehold.it/100x100"
    },
    {
        "id": 345,
        "name": "Matt Hill",
        "img": "http://placehold.it/100x100"
    },
    {
        "id": 346,
        "name": "Jessica Bedford",
        "img": "http://placehold.it/100x100"
    },
    {
        "id": 347,
        "name": "Jessica Alba",
        "img": "http://placehold.it/100x100"
    },
    {
        "id": 348,
        "name": "Scarlett Johansson",
        "img": "http://placehold.it/100x100"
    },
    {
        "id": 349,
        "name": "John Doe",
        "img": "http://placehold.it/100x100"
    },
    {
        "id": 350,
        "name": "Pauline Halen",
        "img": "http://placehold.it/100x100"
    },
    {
        "id": 351,
        "name": "Matt Hill",
        "img": "http://placehold.it/100x100"
    },
    {
        "id": 352,
        "name": "Jessica Bedford",
        "img": "http://placehold.it/100x100"
    },
    {
        "id": 353,
        "name": "Jessica Alba",
        "img": "http://placehold.it/100x100"
    },
    {
        "id": 354,
        "name": "Scarlett Johansson",
        "img": "http://placehold.it/100x100"
    },
    {
        "id": 355,
        "name": "John Doe",
        "img": "http://placehold.it/100x100"
    },
    {
        "id": 356,
        "name": "Pauline Halen",
        "img": "http://placehold.it/100x100"
    },
    {
        "id": 357,
        "name": "Matt Hill",
        "img": "http://placehold.it/100x100"
    },
    {
        "id": 358,
        "name": "Jessica Bedford",
        "img": "http://placehold.it/100x100"
    },
    {
        "id": 359,
        "name": "Jessica Alba",
        "img": "http://placehold.it/100x100"
    },
    {
        "id": 360,
        "name": "Scarlett Johansson",
        "img": "http://placehold.it/100x100"
    },
    {
        "id": 361,
        "name": "John Doe",
        "img": "http://placehold.it/100x100"
    },
    {
        "id": 362,
        "name": "Pauline Halen",
        "img": "http://placehold.it/100x100"
    },
    {
        "id": 363,
        "name": "Matt Hill",
        "img": "http://placehold.it/100x100"
    },
    {
        "id": 364,
        "name": "Jessica Bedford",
        "img": "http://placehold.it/100x100"
    },
    {
        "id": 365,
        "name": "Jessica Alba",
        "img": "http://placehold.it/100x100"
    },
    {
        "id": 366,
        "name": "Scarlett Johansson",
        "img": "http://placehold.it/100x100"
    },
    {
        "id": 367,
        "name": "John Doe",
        "img": "http://placehold.it/100x100"
    },
    {
        "id": 368,
        "name": "Pauline Halen",
        "img": "http://placehold.it/100x100"
    },
    {
        "id": 369,
        "name": "Matt Hill",
        "img": "http://placehold.it/100x100"
    },
    {
        "id": 370,
        "name": "Jessica Bedford",
        "img": "http://placehold.it/100x100"
    },
    {
        "id": 371,
        "name": "Jessica Alba",
        "img": "http://placehold.it/100x100"
    },
    {
        "id": 372,
        "name": "Scarlett Johansson",
        "img": "http://placehold.it/100x100"
    },
    {
        "id": 373,
        "name": "John Doe",
        "img": "http://placehold.it/100x100"
    },
    {
        "id": 374,
        "name": "Pauline Halen",
        "img": "http://placehold.it/100x100"
    },
    {
        "id": 375,
        "name": "Matt Hill",
        "img": "http://placehold.it/100x100"
    },
    {
        "id": 376,
        "name": "Jessica Bedford",
        "img": "http://placehold.it/100x100"
    },
    {
        "id": 377,
        "name": "Jessica Alba",
        "img": "http://placehold.it/100x100"
    },
    {
        "id": 378,
        "name": "Scarlett Johansson",
        "img": "http://placehold.it/100x100"
    },
    {
        "id": 379,
        "name": "John Doe",
        "img": "http://placehold.it/100x100"
    },
    {
        "id": 380,
        "name": "Pauline Halen",
        "img": "http://placehold.it/100x100"
    },
    {
        "id": 381,
        "name": "Matt Hill",
        "img": "http://placehold.it/100x100"
    },
    {
        "id": 382,
        "name": "Jessica Bedford",
        "img": "http://placehold.it/100x100"
    },
    {
        "id": 383,
        "name": "Jessica Alba",
        "img": "http://placehold.it/100x100"
    },
    {
        "id": 384,
        "name": "Scarlett Johansson",
        "img": "http://placehold.it/100x100"
    },
    {
        "id": 385,
        "name": "John Doe",
        "img": "http://placehold.it/100x100"
    },
    {
        "id": 386,
        "name": "Pauline Halen",
        "img": "http://placehold.it/100x100"
    },
    {
        "id": 387,
        "name": "Matt Hill",
        "img": "http://placehold.it/100x100"
    },
    {
        "id": 388,
        "name": "Jessica Bedford",
        "img": "http://placehold.it/100x100"
    },
    {
        "id": 389,
        "name": "Jessica Alba",
        "img": "http://placehold.it/100x100"
    },
    {
        "id": 390,
        "name": "Scarlett Johansson",
        "img": "http://placehold.it/100x100"
    },
    {
        "id": 391,
        "name": "John Doe",
        "img": "http://placehold.it/100x100"
    },
    {
        "id": 392,
        "name": "Pauline Halen",
        "img": "http://placehold.it/100x100"
    },
    {
        "id": 393,
        "name": "Matt Hill",
        "img": "http://placehold.it/100x100"
    },
    {
        "id": 394,
        "name": "Jessica Bedford",
        "img": "http://placehold.it/100x100"
    },
    {
        "id": 395,
        "name": "Jessica Alba",
        "img": "http://placehold.it/100x100"
    },
    {
        "id": 396,
        "name": "Scarlett Johansson",
        "img": "http://placehold.it/100x100"
    },
    {
        "id": 397,
        "name": "John Doe",
        "img": "http://placehold.it/100x100"
    },
    {
        "id": 398,
        "name": "Pauline Halen",
        "img": "http://placehold.it/100x100"
    },
    {
        "id": 399,
        "name": "Matt Hill",
        "img": "http://placehold.it/100x100"
    },
    {
        "id": 400,
        "name": "Jessica Bedford",
        "img": "http://placehold.it/100x100"
    }
]